__init__.py
exceptions.py
extractor.py
processor.py
validator.py
llm_code_extractor-0.1.1.dist-info/METADATA
llm_code_extractor-0.1.1.dist-info/WHEEL
llm_code_extractor-0.1.1.dist-info/top_level.txt
llm_code_extractor-0.1.1.dist-info/RECORD
